envdatareader/__init__.py
envdatareader/envdatareader.py
envdatareader-1.3.dist-info/METADATA
envdatareader-1.3.dist-info/WHEEL
envdatareader-1.3.dist-info/top_level.txt
envdatareader-1.3.dist-info/RECORD
