Metadata-Version: 2.1
Name: envdatareader
Version: 1.3
Summary: ('envdatareader - это библиотека на Python для управления ', 'переменными окружения в приложениях...')
Home-page: https://github.com/HermitBroccoli/EnvUtil
Author: hBroccoli
License: MIT
Classifier: License :: OSI Approved :: MIT License
Classifier: Programming Language :: Python :: 3.7
Classifier: Programming Language :: Python :: 3.8
Classifier: Programming Language :: Python :: 3.9
Classifier: Programming Language :: Python :: 3.10
Classifier: Programming Language :: Python :: 3.11
Classifier: Programming Language :: Python :: 3.12
Requires-Python: >=3.7
Requires-Dist: python-dotenv
